avishan/__init__.py
avishan/admin.py
avishan/apps.py
avishan/descriptor.py
avishan/exceptions.py
avishan/middlewares.py
avishan/models.py
avishan/models_extensions.py
avishan/requirements.txt
avishan/tasks.py
avishan/urls.py
avishan/utils.py
avishan/__pycache__/__init__.cpython-36.pyc
avishan/__pycache__/admin.cpython-36.pyc
avishan/__pycache__/descriptor.cpython-36.pyc
avishan/__pycache__/exceptions.cpython-36.pyc
avishan/__pycache__/middlewares.cpython-36.pyc
avishan/__pycache__/models.cpython-36.pyc
avishan/__pycache__/models_extensions.cpython-36.pyc
avishan/__pycache__/urls.cpython-36.pyc
avishan/__pycache__/utils.cpython-36.pyc
avishan/configure/__init__.py
avishan/configure/__pycache__/__init__.cpython-36.pyc
avishan/libraries/__init__.py
avishan/libraries/__pycache__/__init__.cpython-36.pyc
avishan/libraries/chayi/__init__.py
avishan/libraries/dbml/__init__.py
avishan/libraries/faker/__init__.py
avishan/libraries/faker/providers.py
avishan/libraries/faker/__pycache__/__init__.cpython-36.pyc
avishan/libraries/firebase/__init__.py
avishan/libraries/kavenegar/__init__.py
avishan/libraries/mailgun/__init__.py
avishan/libraries/mailgun/functions.py
avishan/libraries/mailgun/__pycache__/__init__.cpython-36.pyc
avishan/libraries/mailgun/__pycache__/functions.cpython-36.pyc
avishan/libraries/map_ir/__init__.py
avishan/libraries/neshan/__init__.py
avishan/libraries/openapi3/__init__.py
avishan/libraries/openapi3/__pycache__/__init__.cpython-36.pyc
avishan/management/__init__.py
avishan/management/__pycache__/__init__.cpython-36.pyc
avishan/management/commands/__init__.py
avishan/management/commands/avishan_clean_request_tracks.py
avishan/management/commands/avishan_configure.py
avishan/management/commands/avishan_import_cities_from_back4app.py
avishan/management/commands/avishan_import_countries.py
avishan/management/commands/avishan_import_countries_from_back4app.py
avishan/management/commands/__pycache__/__init__.cpython-36.pyc
django_avishan-0.5.34.dist-info/LICENSE
django_avishan-0.5.34.dist-info/METADATA
django_avishan-0.5.34.dist-info/WHEEL
django_avishan-0.5.34.dist-info/top_level.txt
django_avishan-0.5.34.dist-info/RECORD
